exsu/__init__.py
exsu/app_tools.py
exsu/dili.py
exsu/git_tools.py
exsu/packages.py
exsu/param_tools.py
exsu/report.py
exsu-0.6.0.dist-info/LICENSE
exsu-0.6.0.dist-info/METADATA
exsu-0.6.0.dist-info/WHEEL
exsu-0.6.0.dist-info/top_level.txt
exsu-0.6.0.dist-info/RECORD
