Metadata-Version: 2.1
Name: exsu
Version: 0.6.0
Summary: Experiment support tools
Home-page: https://github.com/mjirik/exsu
Author: Miroslav Jirik
Author-email: miroslav.jirik@gmail.com
License: MIT
Platform: UNKNOWN
Classifier: Development Status :: 3 - Alpha
Classifier: Intended Audience :: Developers
Classifier: Topic :: Scientific/Engineering :: Bio-Informatics
Classifier: License :: OSI Approved :: BSD License
Classifier: Programming Language :: Python :: 3.7
Classifier: Programming Language :: Python :: 3.6
License-File: LICENSE
